fastkafka/__init__.py
fastkafka/_aiokafka_imports.py
fastkafka/_cli.py
fastkafka/_cli_docs.py
fastkafka/_cli_testing.py
fastkafka/_docusaurus_helper.py
fastkafka/_helpers.py
fastkafka/_modidx.py
fastkafka/_server.py
fastkafka/encoder.py
fastkafka/executors.py
fastkafka/testing.py
fastkafka/_application/__init__.py
fastkafka/_application/app.py
fastkafka/_application/tester.py
fastkafka/_components/__init__.py
fastkafka/_components/_subprocess.py
fastkafka/_components/aiokafka_consumer_loop.py
fastkafka/_components/asyncapi.py
fastkafka/_components/benchmarking.py
fastkafka/_components/docs_dependencies.py
fastkafka/_components/helpers.py
fastkafka/_components/logger.py
fastkafka/_components/meta.py
fastkafka/_components/producer_decorator.py
fastkafka/_components/task_streaming.py
fastkafka/_components/test_dependencies.py
fastkafka/_components/encoder/__init__.py
fastkafka/_components/encoder/avro.py
fastkafka/_components/encoder/json.py
fastkafka/_testing/__init__.py
fastkafka/_testing/apache_kafka_broker.py
fastkafka/_testing/in_memory_broker.py
fastkafka/_testing/local_redpanda_broker.py
fastkafka/_testing/test_utils.py
fastkafka-0.8.0.dist-info/LICENSE
fastkafka-0.8.0.dist-info/METADATA
fastkafka-0.8.0.dist-info/WHEEL
fastkafka-0.8.0.dist-info/entry_points.txt
fastkafka-0.8.0.dist-info/top_level.txt
fastkafka-0.8.0.dist-info/RECORD
