Metadata-Version: 2.1
Name: fastkafka
Version: 0.8.0
Summary: FastKafka is a powerful and easy-to-use Python library for building asynchronous web services that interact with Kafka topics. Built on top of FastAPI, Starlette, Pydantic, AIOKafka and AsyncAPI, FastKafka simplifies the process of writing producers and consumers for Kafka topics.
Home-page: https://github.com/airtai/fastkafka
Author: airt
Author-email: info@airt.ai
License: Apache Software License 2.0
Project-URL: Bug Tracker, https://github.com/airtai/fastkafka/issues
Project-URL: CI, https://github.com/airtai/fastkafka/actions
Project-URL: Documentation, https://fastkafka.airt.ai/
Project-URL: Tutorial, https://colab.research.google.com/github/airtai/fastkafka/blob/main/nbs/guides/Guide_00_FastKafka_Demo.ipynb
Keywords: nbdev jupyter notebook python kafka
Platform: UNKNOWN
Classifier: Development Status :: 5 - Production/Stable
Classifier: Intended Audience :: Developers
Classifier: Natural Language :: English
Classifier: Programming Language :: Python :: 3.8
Classifier: Programming Language :: Python :: 3.9
Classifier: Programming Language :: Python :: 3.10
Classifier: Programming Language :: Python :: 3.11
Classifier: License :: OSI Approved :: Apache Software License
Requires-Python: >=3.8
License-File: LICENSE
Requires-Dist: aiokafka (>=0.8.0)
Requires-Dist: anyio (>=3.0)
Requires-Dist: asyncer (>=0.0.2)
Requires-Dist: docstring-parser (>=0.15)
Requires-Dist: nest-asyncio (>=1.5.6)
Requires-Dist: pydantic (>=2.0)
Requires-Dist: tqdm (>=4.62)
Requires-Dist: typer (>=0.7.0)
Requires-Dist: psutil (>=5.9.5) ; platform_system == "Windows"
Provides-Extra: avro
Requires-Dist: fastavro (>=1.7.3) ; extra == 'avro'
Provides-Extra: dev
Requires-Dist: PyYAML (>=5.3.1) ; extra == 'dev'
Requires-Dist: aiohttp (>=3.8.4) ; extra == 'dev'
Requires-Dist: bandit (==1.7.5) ; extra == 'dev'
Requires-Dist: black (==23.3.0) ; extra == 'dev'
Requires-Dist: email-validator (>=2.0.0) ; extra == 'dev'
Requires-Dist: fastapi (>=0.100.0b2) ; extra == 'dev'
Requires-Dist: fastavro (>=1.7.3) ; extra == 'dev'
Requires-Dist: install-jdk (==0.3.0) ; extra == 'dev'
Requires-Dist: ipython (<8.13) ; extra == 'dev'
Requires-Dist: ipywidgets (<=8.0.4,>=8.0) ; extra == 'dev'
Requires-Dist: isort (==5.12.0) ; extra == 'dev'
Requires-Dist: mypy (==1.3.0) ; extra == 'dev'
Requires-Dist: nbconvert (>=7.2.9) ; extra == 'dev'
Requires-Dist: nbdev-mkdocs (==0.6.0) ; extra == 'dev'
Requires-Dist: nbformat (>=5.7.3) ; extra == 'dev'
Requires-Dist: nbqa (==1.6.3) ; extra == 'dev'
Requires-Dist: numpy (>=1.21.0) ; extra == 'dev'
Requires-Dist: pandas (>=1.2.0) ; extra == 'dev'
Requires-Dist: pre-commit (==3.3.1) ; extra == 'dev'
Requires-Dist: pytest (==7.3.1) ; extra == 'dev'
Requires-Dist: requests (>=2.20) ; extra == 'dev'
Requires-Dist: scikit-learn (==1.2.1) ; extra == 'dev'
Requires-Dist: semgrep (==1.21.0) ; extra == 'dev'
Requires-Dist: uvicorn (==0.22.0) ; extra == 'dev'
Provides-Extra: docs
Requires-Dist: PyYAML (>=5.3.1) ; extra == 'docs'
Requires-Dist: aiohttp (>=3.8.4) ; extra == 'docs'
Provides-Extra: test
Requires-Dist: install-jdk (==0.3.0) ; extra == 'test'
Requires-Dist: ipywidgets (<=8.0.4,>=8.0) ; extra == 'test'
Requires-Dist: requests (>=2.20) ; extra == 'test'
